audiomate/__init__.py
audiomate/logutil.py
audiomate/annotations/__init__.py
audiomate/annotations/label.py
audiomate/annotations/label_list.py
audiomate/annotations/relabeling.py
audiomate/containers/__init__.py
audiomate/containers/audio.py
audiomate/containers/container.py
audiomate/containers/features.py
audiomate/corpus/__init__.py
audiomate/corpus/base.py
audiomate/corpus/corpus.py
audiomate/corpus/conversion/__init__.py
audiomate/corpus/conversion/base.py
audiomate/corpus/conversion/wav.py
audiomate/corpus/io/__init__.py
audiomate/corpus/io/aed.py
audiomate/corpus/io/audio_mnist.py
audiomate/corpus/io/base.py
audiomate/corpus/io/broadcast.py
audiomate/corpus/io/common_voice.py
audiomate/corpus/io/default.py
audiomate/corpus/io/downloader.py
audiomate/corpus/io/esc.py
audiomate/corpus/io/fluent_speech.py
audiomate/corpus/io/folder.py
audiomate/corpus/io/free_spoken_digits.py
audiomate/corpus/io/gtzan.py
audiomate/corpus/io/kaldi.py
audiomate/corpus/io/librispeech.py
audiomate/corpus/io/mailabs.py
audiomate/corpus/io/mozilla_deepspeech.py
audiomate/corpus/io/musan.py
audiomate/corpus/io/nvidia_jasper.py
audiomate/corpus/io/rouen.py
audiomate/corpus/io/speech_commands.py
audiomate/corpus/io/swc.py
audiomate/corpus/io/tatoeba.py
audiomate/corpus/io/timit.py
audiomate/corpus/io/tuda.py
audiomate/corpus/io/urbansound.py
audiomate/corpus/io/voxforge.py
audiomate/corpus/io/wav2letter.py
audiomate/corpus/io/data/common-voice/invalid_utterances.json
audiomate/corpus/io/data/mailabs/invalid_utterances.json
audiomate/corpus/io/data/swc/invalid_utterances.json
audiomate/corpus/io/data/tuda/invalid_utterances.json
audiomate/corpus/io/data/voxforge/invalid_utterances.json
audiomate/corpus/subset/__init__.py
audiomate/corpus/subset/selection.py
audiomate/corpus/subset/splitting.py
audiomate/corpus/subset/subview.py
audiomate/corpus/subset/utils.py
audiomate/corpus/validation/__init__.py
audiomate/corpus/validation/base.py
audiomate/corpus/validation/combine.py
audiomate-6.0.0.dist-info/LICENSE
audiomate-6.0.0.dist-info/METADATA
audiomate-6.0.0.dist-info/WHEEL
audiomate-6.0.0.dist-info/top_level.txt
audiomate-6.0.0.dist-info/RECORD
