Metadata-Version: 2.1
Name: audiomate
Version: 6.0.0
Summary: Audiomate is a library for working with audio datasets.
Home-page: https://github.com/ynop/audiomate
Author: Matthias Buechi, Andreas Ahlenstorf
Author-email: buec@zhaw.ch
License: MIT
Download-URL: https://github.com/ynop/audiomate/releases
Keywords: audio music sound corpus dataset
Platform: UNKNOWN
Classifier: Intended Audience :: Science/Research
Classifier: License :: OSI Approved :: MIT License
Classifier: Programming Language :: Python :: 3.6
Classifier: Programming Language :: Python :: 3.7
Classifier: Programming Language :: Python :: 3.8
Classifier: Topic :: Scientific/Engineering :: Human Machine Interfaces
Requires-Dist: audioread (==2.1.8)
Requires-Dist: numpy (==1.18.1)
Requires-Dist: scipy (==1.4.1)
Requires-Dist: librosa (==0.7.2)
Requires-Dist: h5py (==2.10.0)
Requires-Dist: networkx (==2.4)
Requires-Dist: requests (==2.23.0)
Requires-Dist: intervaltree (==3.0.2)
Requires-Dist: sox (==1.3.7)
Requires-Dist: PGet (==0.5.0)
Requires-Dist: numba (==0.49.1)
Provides-Extra: ci
Requires-Dist: flake8 (==3.7.9) ; extra == 'ci'
Requires-Dist: flake8-quotes (==2.1.1) ; extra == 'ci'
Provides-Extra: dev
Requires-Dist: click (==7.0) ; extra == 'dev'
Requires-Dist: pytest (==5.3.5) ; extra == 'dev'
Requires-Dist: pytest-runner (==5.2) ; extra == 'dev'
Requires-Dist: pytest-cov (==2.8.1) ; extra == 'dev'
Requires-Dist: requests-mock (==1.7.0) ; extra == 'dev'
Requires-Dist: Sphinx (==2.4.4) ; extra == 'dev'
Requires-Dist: sphinx-rtd-theme (==0.4.3) ; extra == 'dev'
Requires-Dist: pytest-benchmark (==3.2.3) ; extra == 'dev'
